[
  {
    "id": 178682,
    "participant_id": 2447,
    "sport_id": 1,
    "league_id": 271,
    "season_id": 18334,
    "stage_id": 77453567,
    "group_id": null,
    "round_id": 271936,
    "standing_rule_id": 12402,
    "position": 1,
    "result": "equal",
    "points": 44
  },
  {
    "id": 178684,
    "participant_id": 85,
    "sport_id": 1,
    "league_id": 271,
    "season_id": 18334,
    "stage_id": 77453566,
    "group_id": null,
    "round_id": 271940,
    "standing_rule_id": 12399,
    "position": 1,
    "result": "equal",
    "points": 68
  },
  {
    "id": 23431,
    "participant_id": 85,
    "sport_id": 1,
    "league_id": 271,
    "season_id": 18334,
    "stage_id": 77453568,
    "group_id": null,
    "round_id": 251753,
    "standing_rule_id": 6911,
    "position": 1,
    "result": "equal",
    "points": 48
  },
  {
    "id": 178695,
    "participant_id": 1789,
    "sport_id": 1,
    "league_id": 271,
    "season_id": 18334,
    "stage_id": 77453567,
    "group_id": null,
    "round_id": 271936,
    "standing_rule_id": null,
    "position": 2,
    "result": "equal",
    "points": 38
  },
  {
    "id": 23432,
    "participant_id": 939,
    "sport_id": 1,
    "league_id": 271,
    "season_id": 18334,
    "stage_id": 77453568,
    "group_id": null,
    "round_id": 251753,
    "standing_rule_id": 6912,
    "position": 2,
    "result": "up",
    "points": 42
  },
  {
    "id": 178669,
    "participant_id": 939,
    "sport_id": 1,
    "league_id": 271,
    "season_id": 18334,
    "stage_id": 77453566,
    "group_id": null,
    "round_id": 271940,
    "standing_rule_id": 12398,
    "position": 2,
    "result": "equal",
    "points": 65
  },
  {
    "id": 178701,
    "participant_id": 2394,
    "sport_id": 1,
    "league_id": 271,
    "season_id": 18334,
    "stage_id": 77453567,
    "group_id": null,
    "round_id": 271936,
    "standing_rule_id": null,
    "position": 3,
    "result": "equal",
    "points": 36
  },
  {
    "id": 178693,
    "participant_id": 86,
    "sport_id": 1,
    "league_id": 271,
    "season_id": 18334,
    "stage_id": 77453566,
    "group_id": null,
    "round_id": 271940,
    "standing_rule_id": 12400,
    "position": 3,
    "result": "equal",
    "points": 49
  },
  {
    "id": 23436,
    "participant_id": 293,
    "sport_id": 1,
    "league_id": 271,
    "season_id": 18334,
    "stage_id": 77453568,
    "group_id": null,
    "round_id": 251753,
    "standing_rule_id": 6913,
    "position": 3,
    "result": "down",
    "points": 40
  },
  {
    "id": 23433,
    "participant_id": 1020,
    "sport_id": 1,
    "league_id": 271,
    "season_id": 18334,
    "stage_id": 77453568,
    "group_id": null,
    "round_id": 251753,
    "standing_rule_id": 6914,
    "position": 4,
    "result": "equal",
    "points": 38
  },
  {
    "id": 178713,
    "participant_id": 293,
    "sport_id": 1,
    "league_id": 271,
    "season_id": 18334,
    "stage_id": 77453566,
    "group_id": null,
    "round_id": 271940,
    "standing_rule_id": 12401,
    "position": 4,
    "result": "equal",
    "points": 48
  },
  {
    "id": 178725,
    "participant_id": 2905,
    "sport_id": 1,
    "league_id": 271,
    "season_id": 18334,
    "stage_id": 77453567,
    "group_id": null,
    "round_id": 271936,
    "standing_rule_id": null,
    "position": 4,
    "result": "equal",
    "points": 30
  },
  {
    "id": 178708,
    "participant_id": 7466,
    "sport_id": 1,
    "league_id": 271,
    "season_id": 18334,
    "stage_id": 77453567,
    "group_id": null,
    "round_id": 271936,
    "standing_rule_id": 12404,
    "position": 5,
    "result": "equal",
    "points": 29
  },
  {
    "id": 23441,
    "participant_id": 2356,
    "sport_id": 1,
    "league_id": 271,
    "season_id": 18334,
    "stage_id": 77453568,
    "group_id": null,
    "round_id": 251753,
    "standing_rule_id": 6915,
    "position": 5,
    "result": "equal",
    "points": 33
  },
  {
    "id": 178723,
    "participant_id": 1020,
    "sport_id": 1,
    "league_id": 271,
    "season_id": 18334,
    "stage_id": 77453566,
    "group_id": null,
    "round_id": 271940,
    "standing_rule_id": null,
    "position": 5,
    "result": "equal",
    "points": 45
  },
  {
    "id": 178703,
    "participant_id": 2356,
    "sport_id": 1,
    "league_id": 271,
    "season_id": 18334,
    "stage_id": 77453566,
    "group_id": null,
    "round_id": 271940,
    "standing_rule_id": null,
    "position": 6,
    "result": "equal",
    "points": 43
  },
  {
    "id": 23442,
    "participant_id": 86,
    "sport_id": 1,
    "league_id": 271,
    "season_id": 18334,
    "stage_id": 77453568,
    "group_id": null,
    "round_id": 251753,
    "standing_rule_id": 6916,
    "position": 6,
    "result": "equal",
    "points": 31
  },
  {
    "id": 178718,
    "participant_id": 390,
    "sport_id": 1,
    "league_id": 271,
    "season_id": 18334,
    "stage_id": 77453567,
    "group_id": null,
    "round_id": 271936,
    "standing_rule_id": 12403,
    "position": 6,
    "result": "equal",
    "points": 23
  },
  {
    "id": 23440,
    "participant_id": 2447,
    "sport_id": 1,
    "league_id": 271,
    "season_id": 18334,
    "stage_id": 77453568,
    "group_id": null,
    "round_id": 251753,
    "standing_rule_id": 6917,
    "position": 7,
    "result": "equal",
    "points": 27
  },
  {
    "id": 23438,
    "participant_id": 2905,
    "sport_id": 1,
    "league_id": 271,
    "season_id": 18334,
    "stage_id": 77453568,
    "group_id": null,
    "round_id": 251753,
    "standing_rule_id": 6918,
    "position": 8,
    "result": "equal",
    "points": 26
  },
  {
    "id": 23439,
    "participant_id": 1789,
    "sport_id": 1,
    "league_id": 271,
    "season_id": 18334,
    "stage_id": 77453568,
    "group_id": null,
    "round_id": 251753,
    "standing_rule_id": 6919,
    "position": 9,
    "result": "equal",
    "points": 21
  },
  {
    "id": 23435,
    "participant_id": 2394,
    "sport_id": 1,
    "league_id": 271,
    "season_id": 18334,
    "stage_id": 77453568,
    "group_id": null,
    "round_id": 251753,
    "standing_rule_id": 6920,
    "position": 10,
    "result": "equal",
    "points": 21
  },
  {
    "id": 23434,
    "participant_id": 7466,
    "sport_id": 1,
    "league_id": 271,
    "season_id": 18334,
    "stage_id": 77453568,
    "group_id": null,
    "round_id": 251753,
    "standing_rule_id": 6921,
    "position": 11,
    "result": "equal",
    "points": 16
  },
  {
    "id": 23437,
    "participant_id": 390,
    "sport_id": 1,
    "league_id": 271,
    "season_id": 18334,
    "stage_id": 77453568,
    "group_id": null,
    "round_id": 251753,
    "standing_rule_id": 6922,
    "position": 12,
    "result": "equal",
    "points": 13
  }
]
